src/entrpy/__init__.py
entrpy-0.0.1.dist-info/LICENSE
entrpy-0.0.1.dist-info/METADATA
entrpy-0.0.1.dist-info/WHEEL
entrpy-0.0.1.dist-info/RECORD
